paginationtester/__init__.py
paginationtester/api_helper.py
paginationtester/configuration.py
paginationtester/paginationtester_client.py
paginationtester/controllers/__init__.py
paginationtester/controllers/base_controller.py
paginationtester/controllers/transaction_controller.py
paginationtester/exceptions/__init__.py
paginationtester/exceptions/api_exception.py
paginationtester/http/__init__.py
paginationtester/http/http_call_back.py
paginationtester/http/http_method_enum.py
paginationtester/http/http_request.py
paginationtester/http/http_response.py
paginationtester/models/__init__.py
paginationtester/models/links.py
paginationtester/models/transaction.py
paginationtester/models/transactions_cursored.py
paginationtester/models/transactions_linked.py
paginationtester/models/transactions_offset.py
paginationtester/utilities/__init__.py
paginationtester/utilities/file_wrapper.py
qa_sdk-1.8.9.dist-info/licenses/LICENSE
qa_sdk-1.8.9.dist-info/METADATA
qa_sdk-1.8.9.dist-info/WHEEL
qa_sdk-1.8.9.dist-info/top_level.txt
qa_sdk-1.8.9.dist-info/RECORD
