Metadata-Version: 2.4
Name: qa-sdk
Version: 1.8.9
Summary: TEst
Author-email: cfd <tahaali2000@hotmail.com>
Project-URL: Documentation, https://www.google.com/search?q=cloudflare&rlz=1C1ONGR_enPK1153PK1153&oq=&gs_lcrp=EgZjaHJvbWUqCQgAEEUYOxjCAzIJCAAQRRg7GMIDMgkIARBFGDsYwgMyCQgCEEUYOxjCAzIJCAMQRRg7GMIDMgkIBBBFGDsYwgMyCQgFEEUYOxjCAzIJCAYQRRg7GMIDMgkIBxBFGDsYwgPSAQk1OTY3MGowajeoAgiwAgHxBUBAiHbEfHVx&sourceid=chrome&ie=UTF-8
Keywords: qa
Requires-Python: >=3.7
License-File: LICENSE
Requires-Dist: apimatic-core>=0.2.17,~=0.2.0
Requires-Dist: apimatic-core-interfaces>=0.1.5,~=0.1.0
Requires-Dist: apimatic-requests-client-adapter>=0.1.6,~=0.1.0
Provides-Extra: testutils
Requires-Dist: pytest>=7.2.2; extra == "testutils"
Dynamic: license-file
